larray/__init__.py
larray/example.py
larray/random.py
larray/core/__init__.py
larray/core/abstractbases.py
larray/core/array.py
larray/core/axis.py
larray/core/checked.py
larray/core/constants.py
larray/core/expr.py
larray/core/group.py
larray/core/metadata.py
larray/core/misc.py
larray/core/npufuncs.py
larray/core/plot.py
larray/core/session.py
larray/core/ufuncs.py
larray/extra/__init__.py
larray/extra/ipfp.py
larray/inout/__init__.py
larray/inout/common.py
larray/inout/csv.py
larray/inout/excel.py
larray/inout/hdf.py
larray/inout/misc.py
larray/inout/pandas.py
larray/inout/pickle.py
larray/inout/sas.py
larray/inout/session.py
larray/inout/stata.py
larray/inout/xw_excel.py
larray/inout/xw_reporting.py
larray/ipfp/__init__.py
larray/tests/__init__.py
larray/tests/common.py
larray/tests/generate_data.py
larray/tests/test_array.py
larray/tests/test_axis.py
larray/tests/test_axiscollection.py
larray/tests/test_checked_session.py
larray/tests/test_example.py
larray/tests/test_excel.py
larray/tests/test_group.py
larray/tests/test_ipfp.py
larray/tests/test_options.py
larray/tests/test_session.py
larray/tests/data/births_and_deaths.xlsx
larray/tests/data/demography.h5
larray/tests/data/demography.xlsx
larray/tests/data/demography_eurostat.h5
larray/tests/data/demography_eurostat.xlsx
larray/tests/data/examples.h5
larray/tests/data/examples.xlsx
larray/tests/data/hh.csv
larray/tests/data/missing_axis_name.csv
larray/tests/data/missing_values_3d.csv
larray/tests/data/narrow_2d.csv
larray/tests/data/pop.csv
larray/tests/data/population_only.xlsx
larray/tests/data/qx.csv
larray/tests/data/test.h5
larray/tests/data/test.xlsx
larray/tests/data/test1d.csv
larray/tests/data/test1d_liam2.csv
larray/tests/data/test1d_narrow.csv
larray/tests/data/test2d.csv
larray/tests/data/test2d_classic.csv
larray/tests/data/test2d_classic_narrow.csv
larray/tests/data/test2d_narrow.csv
larray/tests/data/test3d.csv
larray/tests/data/test3d_narrow.csv
larray/tests/data/test5d_eurostat.csv
larray-0.35.dist-info/licenses/LICENSE
larray-0.35.dist-info/METADATA
larray-0.35.dist-info/WHEEL
larray-0.35.dist-info/top_level.txt
larray-0.35.dist-info/RECORD
