Metadata-Version: 2.4
Name: larray
Version: 0.35
Summary: N-D labeled arrays in Python
Author: Geert Bryon, Johan Duyck
Author-email: Gaetan de Menten <gdementen@gmail.com>, Alix Damman <ald@plan.be>
License-Expression: GPL-3.0-only
Project-URL: homepage, https://github.com/larray-project/larray
Project-URL: repository, https://github.com/larray-project/larray
Project-URL: issues, https://github.com/larray-project/larray/issues
Project-URL: documentation, https://larray.readthedocs.io/en/stable/
Classifier: Development Status :: 4 - Beta
Classifier: Operating System :: OS Independent
Classifier: Intended Audience :: Science/Research
Classifier: Intended Audience :: Developers
Classifier: Programming Language :: Python
Classifier: Programming Language :: Python :: 3
Classifier: Programming Language :: Python :: 3.9
Classifier: Programming Language :: Python :: 3.10
Classifier: Programming Language :: Python :: 3.11
Classifier: Programming Language :: Python :: 3.12
Classifier: Programming Language :: Python :: 3.13
Classifier: Programming Language :: Python :: 3.14
Classifier: Topic :: Scientific/Engineering
Classifier: Topic :: Software Development :: Libraries
Requires-Python: >=3.9
License-File: LICENSE
Requires-Dist: numpy>=1.22
Requires-Dist: pandas>=0.20.0
Provides-Extra: test
Requires-Dist: pytest; extra == "test"
Dynamic: license-file
